{
  "entity": "event",
  "account_id": "acc_PsGxwfWW0qybUl",
  "event": "payment.authorized",
  "contains": [
    "payment"
  ],
  "payload": {
    "payment": {
      "entity": {
        "id": "pay_QwUVldIhjfjsJu",
        "entity": "payment",
        "amount": 53760,
        "currency": "INR",
        "status": "authorized",
        "order_id": "order_QwUVgEc0zTMYbt",
        "invoice_id": null,
        "international": false,
        "method": "netbanking",
        "amount_refunded": 0,
        "refund_status": null,
        "captured": false,
        "description": "mathematics",
        "card_id": null,
        "bank": "CNRB",
        "wallet": null,
        "vpa": null,
        "email": "sandeep@gmail.com",
        "contact": "+919999999999",
        "notes": {
          "name": "sandeep",
          "user": "6880c53fdafe086de5ea312a",
          "ebook": "687b5bec3f647858ed689323",
          "discount": "4"
        },
        "fee": null,
        "tax": null,
        "error_code": null,
        "error_description": null,
        "error_source": null,
        "error_step": null,
        "error_reason": null,
        "acquirer_data": {
          "bank_transaction_id": "5725331"
        },
        "created_at": 1753269829
      }
    }
  },
  "created_at": 1753269832
}